<reveDiagram
  desc="Powered by FlowWright"
  testMode="false"
  testModeUserID=""
  schemaVersion="v2"
  defID="eca1c36c-fad8-4d30-82d3-45a61fac3243">
  <figures>
    <figure
      id="651975b3-5084-4ad5-9676-df5dfc58d207"
      name="start"
      type="start"
      x="50"
      y="220"
      isValid="true"
      isLocked="False">
      <properties>
        <property
          name="label"><![CDATA[start]]></property>
        <property
          name="type"><![CDATA[start]]></property>
        <property
          name="isValid"><![CDATA[true]]></property>
        <property
          name="itemName"><![CDATA[start]]></property>
        <property
          name="itemDescription"><![CDATA[]]></property>
        <property
          name="variables"><![CDATA[]]></property>
        <property
          name="requiredVars"><![CDATA[]]></property>
        <property
          name="globals"><![CDATA[]]></property>
        <property
          name="requiredGlobals"><![CDATA[]]></property>
        <property
          name="useSingleIteration"><![CDATA[0]]></property>
        <property
          name="businessObjects"><![CDATA[]]></property>
        <property
          name="LogMessage"><![CDATA[]]></property>
        <property
          name="documentation"><![CDATA[]]></property>
        <property
          name="priority"><![CDATA[Medium]]></property>
        <property
          name="errorDef"><![CDATA[]]></property>
        <property
          name="sub-def-name"><![CDATA[]]></property>
        <property
          name="abortDef"><![CDATA[]]></property>
        <property
          name="completeDef"><![CDATA[]]></property>
        <property
          name="instState"><![CDATA[]]></property>
        <property
          name="instPercent"><![CDATA[]]></property>
      </properties>
    </figure>
    <figure
      id="a55b7652-c70f-0a7a-408c-b6d9062013a3"
      name="Publish Msg Text"
      type="clspublishmsmq"
      x="290"
      y="220"
      isValid="true"
      isLocked="False">
      <properties>
        <property
          name="label"><![CDATA[Publish Msg Text]]></property>
        <property
          name="type"><![CDATA[clspublishmsmq]]></property>
        <property
          name="isValid"><![CDATA[true]]></property>
        <property
          name="itemName"><![CDATA[Publish Msg Text]]></property>
        <property
          name="itemDescription"><![CDATA[clsPublishMSMQ]]></property>
        <property
          name="machineName"><![CDATA[FWQA]]></property>
        <property
          name="queueName"><![CDATA[FlowWright]]></property>
        <property
          name="isPublic"><![CDATA[yes]]></property>
        <property
          name="messageLabel"><![CDATA[Test MSMQ]]></property>
        <property
          name="messageBody"><![CDATA[Sample  Test from MSMQ Service]]></property>
        <property
          name="LogMessage"><![CDATA[clsPublishMSMQ - Variable.createdOn]]></property>
        <property
          name="documentation"><![CDATA[clsPublishMSMQ - Variable.initiatorName]]></property>
        <property
          name="instState"><![CDATA[MSMQ Step]]></property>
        <property
          name="instPercent"><![CDATA[100]]></property>
      </properties>
    </figure>
  </figures>
  <connections>
    <connection
      id="999d86dc-3551-fe92-e792-144a744b4b5b"
      label=""
      size="5"
      type=""
      srcParentID="651975b3-5084-4ad5-9676-df5dfc58d207"
      srcParentType="start"
      trgParentID="a55b7652-c70f-0a7a-408c-b6d9062013a3"
      trgParentType="clspublishmsmq"
      router="junction"
      color="0000ff"
      lblx="190"
      lbly="240"
      style="shape=connector;labelBackgroundColor=#ffffff;endArrow=classic;fontSize=12;fontFamily=Helvetica;align=center;verticalAlign=middle;rounded=1;strokeColor=#0000ff;fontColor=#000000;edgeStyle=orthogonalEdgeStyle;jumpStyle=arc;jumpSize=6;html=1;jettySize=auto;orthogonalLoop=1;strokeWidth=5;whiteSpace=wrap;labelWidth=150;fontStyle=2"
      srcPortName="eastPort"
      trgPortName="westPort">
      <properties>
        <property
          name="label"><![CDATA[]]></property>
        <property
          name="type"><![CDATA[]]></property>
        <property
          name="linkPriority"><![CDATA[0]]></property>
      </properties>
      <line>
        <point
          x="90"
          y="240" />
        <point
          x="290"
          y="240" />
      </line>
    </connection>
  </connections>
  <comments></comments>
</reveDiagram>