<reveDiagram
  desc="Powered by FlowWright"
  testMode="false"
  testModeUserID=""
  schemaVersion="v2"
  defID="737df7d6-ce14-46f0-90bc-3b9d151ca5ff">
  <figures>
    <figure
      id="69ca260e-9436-4bcb-b7ae-2e05e7e0d491"
      name="start"
      type="start"
      x="80"
      y="120"
      isValid="true">
      <properties>
        <property
          name="label"><![CDATA[start]]></property>
        <property
          name="type"><![CDATA[start]]></property>
        <property
          name="itemName"><![CDATA[start]]></property>
        <property
          name="itemDescription"><![CDATA[]]></property>
        <property
          name="variables"><![CDATA[varFilePath:String]]></property>
        <property
          name="requiredVars"><![CDATA[]]></property>
        <property
          name="globals"><![CDATA[]]></property>
        <property
          name="requiredGlobals"><![CDATA[]]></property>
        <property
          name="useSingleIteration"><![CDATA[0]]></property>
        <property
          name="businessObjects"><![CDATA[]]></property>
        <property
          name="LogMessage"><![CDATA[]]></property>
        <property
          name="documentation"><![CDATA[]]></property>
        <property
          name="priority"><![CDATA[Medium]]></property>
        <property
          name="errorDef"><![CDATA[]]></property>
        <property
          name="sub-def-name"><![CDATA[]]></property>
        <property
          name="abortDef"><![CDATA[]]></property>
        <property
          name="completeDef"><![CDATA[]]></property>
        <property
          name="instState"><![CDATA[]]></property>
        <property
          name="instPercent"><![CDATA[]]></property>
        <property
          name="isValid"><![CDATA[true]]></property>
      </properties>
    </figure>
    <figure
      id="4078f243-144e-ba7b-40d7-1ebcda24266a"
      name="Update Variables"
      type="updatevariable"
      x="240"
      y="120"
      isValid="true">
      <properties>
        <property
          name="label"><![CDATA[Update Variables]]></property>
        <property
          name="type"><![CDATA[updatevariable]]></property>
        <property
          name="itemName"><![CDATA[Update Variables]]></property>
        <property
          name="itemDescription"><![CDATA[]]></property>
        <property
          name="updateVariables"><![CDATA[]]></property>
        <property
          name="variableName"><![CDATA[Variable.varFilePath]]></property>
        <property
          name="variableValue"><![CDATA[c:\FlowWright10\wwwroot\TempFiles\Package.dtsx]]></property>
        <property
          name="hasExpression"><![CDATA[no]]></property>
        <property
          name="LogMessage"><![CDATA[]]></property>
        <property
          name="documentation"><![CDATA[]]></property>
        <property
          name="instState"><![CDATA[]]></property>
        <property
          name="instPercent"><![CDATA[]]></property>
        <property
          name="isValid"><![CDATA[true]]></property>
      </properties>
    </figure>
  </figures>
  <connections>
    <connection
      id="a0a406ba-8a13-8d50-2cbd-7172e57022fb"
      label=""
      size="5"
      type=""
      srcParentID="69ca260e-9436-4bcb-b7ae-2e05e7e0d491"
      srcParentType="start"
      trgParentID="4078f243-144e-ba7b-40d7-1ebcda24266a"
      trgParentType="updatevariable"
      router="junction"
      color="0000ff"
      lblx="180"
      lbly="140"
      style="shape=connector;labelBackgroundColor=#ffffff;endArrow=classic;fontSize=15;fontFamily=Helvetica;align=center;verticalAlign=middle;rounded=1;strokeColor=#0000ff;fontColor=#000000;edgeStyle=orthogonalEdgeStyle;jumpStyle=arc;jumpSize=6;html=1;jettySize=auto;orthogonalLoop=1;strokeWidth=5"
      srcPortName="eastPort"
      trgPortName="westPort">
      <properties>
        <property
          name="label"><![CDATA[]]></property>
        <property
          name="type"><![CDATA[]]></property>
        <property
          name="linkPriority"><![CDATA[0]]></property>
      </properties>
      <line>
        <point
          x="120"
          y="140" />
        <point
          x="240"
          y="140" />
      </line>
    </connection>
  </connections>
  <comments></comments>
</reveDiagram>