<reveDiagram
  desc="Powered by FlowWright"
  testMode="false"
  testModeUserID=""
  schemaVersion="v2"
  defID="4f27b86e-a7cb-497f-8220-588c04b262e2">
  <figures>
    <figure
      id="18344ba8-5f05-4f12-a3a2-e7f6c0d3f880"
      name="start"
      type="start"
      x="58"
      y="39"
      isValid="true"
      isLocked="False">
      <properties>
        <property
          name="label"><![CDATA[start]]></property>
        <property
          name="type"><![CDATA[start]]></property>
        <property
          name="isValid"><![CDATA[true]]></property>
        <property
          name="itemName"><![CDATA[start]]></property>
        <property
          name="itemDescription"><![CDATA[]]></property>
        <property
          name="variables"><![CDATA[srcFilePath:String|data:String]]></property>
        <property
          name="requiredVars"><![CDATA[]]></property>
        <property
          name="globals"><![CDATA[]]></property>
        <property
          name="requiredGlobals"><![CDATA[]]></property>
        <property
          name="useSingleIteration"><![CDATA[0]]></property>
        <property
          name="businessObjects"><![CDATA[]]></property>
        <property
          name="logMessage"><![CDATA[]]></property>
        <property
          name="documentation"><![CDATA[]]></property>
      </properties>
    </figure>
    <figure
      id="052fccd7-a8ee-7e91-3723-f725d9914a67"
      name="Rest Call"
      type="restcall"
      x="300"
      y="39"
      isValid="true"
      isLocked="False">
      <properties>
        <property
          name="label"><![CDATA[Rest Call]]></property>
        <property
          name="type"><![CDATA[restcall]]></property>
        <property
          name="isValid"><![CDATA[true]]></property>
        <property
          name="itemName"><![CDATA[Rest Call]]></property>
        <property
          name="itemDescription"><![CDATA[restCall]]></property>
        <property
          name="restURL"><![CDATA[https://dummyjson.com/c/7d4b-4b54-4555-b0e8]]></property>
        <property
          name="method"><![CDATA[POST]]></property>
        <property
          name="userName"><![CDATA[]]></property>
        <property
          name="password"><![CDATA[]]></property>
        <property
          name="payLoadType"><![CDATA[JSON]]></property>
        <property
          name="requestBody"><![CDATA[]]></property>
        <property
          name="responseType"><![CDATA[JSON]]></property>
        <property
          name="sourceFilePath"><![CDATA[variable.srcFilePath]]></property>
        <property
          name="headers"><![CDATA[connect.sid~s%3AyVRTDHfUbqyR2To-Zkv_k2reM5LruNCO.waNhjdtlQD+T4ozvQLpdO+utMEaSABFkIldSkhBZEKw]]></property>
        <property
          name="varToStoreResult"><![CDATA[variable.data]]></property>
        <property
          name="logMessage"><![CDATA[]]></property>
        <property
          name="documentation"><![CDATA[restCall - Variable.initiatorName]]></property>
        <property
          name="LogMessage"><![CDATA[restCall - Variable.createdOn]]></property>
        <property
          name="instState"><![CDATA[Web Services Step]]></property>
        <property
          name="instPercent"><![CDATA[100]]></property>
      </properties>
    </figure>
  </figures>
  <connections>
    <connection
      id="94016ead-fe7c-06af-1f03-a882e8768f04"
      label=""
      size="3"
      type=""
      srcParentID="18344ba8-5f05-4f12-a3a2-e7f6c0d3f880"
      srcParentType="start"
      trgParentID="052fccd7-a8ee-7e91-3723-f725d9914a67"
      trgParentType="restcall"
      router="draw2d.layout.connection.InteractiveManhattanConnectionRouter"
      color="0000ff"
      lblx="199"
      lbly="59"
      style="shape=connector;labelBackgroundColor=#ffffff;endArrow=classic;fontSize=15;fontFamily=Helvetica;align=center;verticalAlign=middle;rounded=1;strokeColor=#0000ff;fontColor=#000000;edgeStyle=orthogonalEdgeStyle;jumpStyle=arc;jumpSize=6;html=1;jettySize=auto;orthogonalLoop=1;strokeWidth=3;whiteSpace=wrap;labelWidth=175;fontStyle=2"
      srcPortName="eastPort"
      trgPortName="westPort">
      <properties>
        <property
          name="label"><![CDATA[]]></property>
        <property
          name="type"><![CDATA[]]></property>
        <property
          name="linkPriority"><![CDATA[0]]></property>
      </properties>
      <line>
        <point
          x="98"
          y="59" />
        <point
          x="300"
          y="59" />
      </line>
    </connection>
  </connections>
  <comments></comments>
</reveDiagram>